TwitchPyRC/__init__.py
TwitchPyRC/exceptions.py
TwitchPyRC/parsers.py
TwitchPyRC/twitch_irc.py
TwitchPyRC/constants/__init__.py
TwitchPyRC/constants/emotes.py
TwitchPyRC/irc_specializations/__init__.py
TwitchPyRC/irc_specializations/command_bot.py
TwitchPyRC/models/__init__.py
TwitchPyRC/models/badge.py
TwitchPyRC/models/base_model.py
TwitchPyRC/models/command_variable.py
TwitchPyRC/models/message_model.py
TwitchPyRC/models/message_variable.py
TwitchPyRC/models/tag_models/__init__.py
TwitchPyRC/models/tag_models/base_tag_model.py
TwitchPyRC/models/tag_models/clear_chat.py
TwitchPyRC/models/tag_models/clear_message.py
TwitchPyRC/models/tag_models/message_sent.py
TwitchPyRC/models/tag_models/whisper.py
TwitchPyRC-1.0.7.dist-info/LICENSE
TwitchPyRC-1.0.7.dist-info/METADATA
TwitchPyRC-1.0.7.dist-info/WHEEL
TwitchPyRC-1.0.7.dist-info/top_level.txt
TwitchPyRC-1.0.7.dist-info/RECORD
