Metadata-Version: 2.1
Name: TwitchPyRC
Version: 1.0.7
Summary: Yet another generic Twitch IRC interface that probably works
Home-page: https://github.com/CPSuperstore/TwitchPyRC
Author: CPSuperstore
Author-email: cpsuperstoreinc@gmail.com
License: MIT
Project-URL: Bug Tracker, https://github.com/CPSuperstore/TwitchPyRC/issues
Keywords: Twitch,IRC,Bot,Chat Bot,Socket,livestream
Classifier: Development Status :: 4 - Beta
Classifier: Intended Audience :: Developers
License-File: LICENSE
